pyuniverse/__init__.py
pyuniverse/core.py
pyuniverse-0.1.1.dist-info/METADATA
pyuniverse-0.1.1.dist-info/WHEEL
pyuniverse-0.1.1.dist-info/top_level.txt
pyuniverse-0.1.1.dist-info/RECORD
