Metadata-Version: 2.4
Name: pyuniverse
Version: 0.1.1
Summary: Create unique Identifiers with ease.
Author: Thomas McCann
License: MIT
Requires-Python: >=3.8
